tvm_book/__about__.py
tvm_book/__init__.py
tvm_book/config/__init__.py
tvm_book/config/env.py
tvm_book/contrib/d2ltvm/__init__.py
tvm_book/contrib/d2ltvm/_d2ltvm.py
tvm_book/contrib/d2ltvm/d2ltvm.py
tvm_book/contrib/mxnet/__init__.py
tvm_book/contrib/mxnet/model.py
tvm_book/contrib/mxnet/tools.py
tvm_book/contrib/tvm/__init__.py
tvm_book/contrib/tvm/config.py
tvm_book/contrib/tvm/model.py
tvm_book/contrib/tvm/quantize.py
tvm_book/contrib/tvm/test.py
tvm_book/data/__init__.py
tvm_book/data/classification.py
tvm_book/data/dataclass.py
tvm_book/data/imagenet/__init__.py
tvm_book/data/imagenet/classification.py
tvm_book/ffi/__init__.py
tvm_book/ffi/libinfo.py
tvm_book/image/__init__.py
tvm_book/image/processing.py
tvm_book/metric/__init__.py
tvm_book/metric/classification.py
tvm_book/mxnet/__init__.py
tvm_book/mxnet/imagenet.py
tvm_book/numpy/__init__.py
tvm_book/numpy/nn/__init__.py
tvm_book/numpy/nn/conv.py
tvm_book/numpy/nn/padding.py
tvm_book/testing/metric.py
tvm_book/testing/relay/let.py
tvm_book/testing/relay/viz.py
tvm_book/tvm_ext/__init__.py
tvm_book/tvm_ext/_ffi_api.py
tvm_book/tvm_ext/libinfo.py
tvm_book/tvm_ext/testing/__init__.py
tvm_book/tvm_ext/testing/_ffi_api.py
tvm_book/tvm_ext/testing/demo.py
tvm_book/tvm_utils/__init__.py
tvm_book/tvm_utils/graph_json.py
tvm_book/tvm_utils/llvm_utils.py
tvm_book/tvm_utils/register_partition.py
tvm_book/tvm_utils/relay_pattern.py
tvm_book/tvm_utils/remote.py
tvm_book/tvm_utils/split_graph.py
tvm_book/tvm_utils/viz_relay.py
tvm_book/utils/__init__.py
tvm_book/vta/__init__.py
tvm_book/vta/remote.py
tvm_book/vta/vtac.py
tvm_book-0.0.20.dist-info/WHEEL
tvm_book-0.0.20.dist-info/METADATA
tvm_book-0.0.20.dist-info/licenses/LICENSE
tvm_book-0.0.20.dist-info/RECORD
