Metadata-Version: 2.1
Name: tvm-book
Version: 0.0.20
Author-email: xinetzone <xinzone@outlook.com>
Requires-Python: >=3.10
Requires-Dist: d2py
Requires-Dist: tqdm
Provides-Extra: dev
Requires-Dist: xgboost; extra == "dev"
Provides-Extra: doc
Requires-Dist: sphinx>5; extra == "doc"
Requires-Dist: mdit-py-plugins; extra == "doc"
Requires-Dist: myst-nb; extra == "doc"
Requires-Dist: xyzstyle; extra == "doc"
Requires-Dist: matplotlib; extra == "doc"
Requires-Dist: sphinx-copybutton; extra == "doc"
Requires-Dist: sphinxcontrib-bibtex; extra == "doc"
Requires-Dist: sphinx-thebe; extra == "doc"
Requires-Dist: sphinx-design; extra == "doc"
Requires-Dist: sphinx-automodapi; extra == "doc"
Requires-Dist: sphinx-sitemap; extra == "doc"
Requires-Dist: sphinx_plotly_directive; extra == "doc"
Requires-Dist: sphinx-comments; extra == "doc"
Requires-Dist: sphinxcontrib-mermaid; extra == "doc"
Requires-Dist: plotly; extra == "doc"
Requires-Dist: sphinxcontrib-websupport; extra == "doc"
Requires-Dist: autodocsumm; extra == "doc"
Project-URL: Documentation, https://xinetzone.github.io/tvm-book
Project-URL: Homepage, https://xinetzone.github.io/tvm-book
Project-URL: Repository, https://github.com/xinetzone/tvm-book
